alpa/__init__.py
alpa/cli/__init__.py
alpa/cli/alpa_repo.py
alpa/cli/base.py
alpa/cli/local_repo.py
alpa/config/__init__.py
alpa/config/alpa_local.py
alpa/config/alpa_repo.py
alpa/config/base.py
alpa/config/metadata.py
alpa/constants.py
alpa/exceptions.py
alpa/gh.py
alpa/git.py
alpa/messages.py
alpa/packit.py
alpa/repository/__init__.py
alpa/repository/base.py
alpa/repository/branch.py
alpa/repository/subdirectory.py
alpa/upstream_integration.py
pyalpa-1.0.0.dist-info/LICENSE
pyalpa-1.0.0.dist-info/METADATA
pyalpa-1.0.0.dist-info/WHEEL
pyalpa-1.0.0.dist-info/entry_points.txt
pyalpa-1.0.0.dist-info/RECORD
