Metadata-Version: 2.1
Name: pyalpa
Version: 1.0.0
Summary: Integration tool with Alpa repository
Home-page: https://github.com/alpa-team/alpa
License: GPLv3
Author: Jiri Kyjovsky
Author-email: j1.kyjovsky@gmail.com
Maintainer: Jiří Kyjovský
Maintainer-email: j1.kyjovsky@gmail.com
Requires-Python: >=3.9,<4.0
Classifier: License :: Other/Proprietary License
Classifier: Programming Language :: Python :: 3
Classifier: Programming Language :: Python :: 3.9
Classifier: Programming Language :: Python :: 3.10
Classifier: Programming Language :: Python :: 3.11
Requires-Dist: click (>=8.0.0)
Requires-Dist: email-validator (>=1.0)
Requires-Dist: pydantic (>=1.8)
Requires-Dist: pygithub (>=1.4)
Requires-Dist: pyyaml (>=5.0)
Requires-Dist: specfile (>=0.13.0)
Project-URL: Repository, https://github.com/alpa-team/alpa
